wuefhwurfwrnbfowief/__inint__.py
wuefhwurfwrnbfowief/fibonacci.py
wuefhwurfwrnbfowief/main.py
wuefhwurfwrnbfowief/visitor.py
wuefhwurfwrnbfowief-0.5.dist-info/LICENSE
wuefhwurfwrnbfowief-0.5.dist-info/METADATA
wuefhwurfwrnbfowief-0.5.dist-info/WHEEL
wuefhwurfwrnbfowief-0.5.dist-info/top_level.txt
wuefhwurfwrnbfowief-0.5.dist-info/RECORD
