Metadata-Version: 2.1
Name: wuefhwurfwrnbfowief
Version: 0.5
Summary: hw_01
License: UNKNOWN
Platform: UNKNOWN
License-File: LICENSE
Requires-Dist: python-version (>="3.6")
